pii_anonymizer/common/__init__.py
pii_anonymizer/common/analyze/__init__.py
pii_anonymizer/common/analyze/analyzer_result.py
pii_anonymizer/common/analyze/detectors/__init__.py
pii_anonymizer/common/analyze/detectors/base_detector.py
pii_anonymizer/common/analyze/detectors/credit_card_detector.py
pii_anonymizer/common/analyze/detectors/email_detector.py
pii_anonymizer/common/analyze/detectors/national_id_detector.py
pii_anonymizer/common/analyze/detectors/phone_number_detector.py
pii_anonymizer/common/analyze/detectors/tests/__init__.py
pii_anonymizer/common/analyze/detectors/tests/test_base_detector.py
pii_anonymizer/common/analyze/detectors/tests/test_credit_card_detector.py
pii_anonymizer/common/analyze/detectors/tests/test_email_detector.py
pii_anonymizer/common/analyze/detectors/tests/test_national_id_detector.py
pii_anonymizer/common/analyze/detectors/tests/test_phone_number_detector.py
pii_anonymizer/common/analyze/detectors/tests/test_thai_id_detector.py
pii_anonymizer/common/analyze/detectors/thai_id_detector.py
pii_anonymizer/common/analyze/filter_overlap_analysis.py
pii_anonymizer/common/analyze/regex.py
pii_anonymizer/common/analyze/tests/__init__.py
pii_anonymizer/common/analyze/tests/test_analyzer_result.py
pii_anonymizer/common/analyze/tests/test_filter_overlap_analysis.py
pii_anonymizer/common/analyze/tests/test_regex.py
pii_anonymizer/common/config_validator.py
pii_anonymizer/common/constants.py
pii_anonymizer/common/file_utils.py
pii_anonymizer/common/get_args.py
pii_anonymizer/common/tests/__init__.py
pii_anonymizer/common/tests/test_config_validator.py
pii_anonymizer/common/tests/test_file_utils.py
pii_anonymizer/key/__main__.py
pii_anonymizer/spark/__init__.py
pii_anonymizer/spark/__main__.py
pii_anonymizer/spark/acquire/__init__.py
pii_anonymizer/spark/acquire/input_parser.py
pii_anonymizer/spark/acquire/tests/__init__.py
pii_anonymizer/spark/acquire/tests/test_input_parser.py
pii_anonymizer/spark/analyze/__init__.py
pii_anonymizer-0.2.5.dist-info/METADATA
pii_anonymizer-0.2.5.dist-info/WHEEL
pii_anonymizer-0.2.5.dist-info/RECORD
