Metadata-Version: 2.1
Name: pii-anonymizer
Version: 0.2.5
Summary: Data Protection Framework is a python library/command line application for identification, anonymization and de-anonymization of Personally Identifiable Information data.
License: MIT
Author: Thoughtworks
Author-email: thoughtworks@thoughtworks.com
Requires-Python: >=3.10,<4.0
Classifier: License :: OSI Approved :: MIT License
Classifier: Programming Language :: Python :: 3
Classifier: Programming Language :: Python :: 3.10
Classifier: Programming Language :: Python :: 3.11
Requires-Dist: cryptography (>=38.0.4,<39.0.0)
Requires-Dist: dask[dataframe] (>=2022.11.1,<2023.0.0)
Requires-Dist: fastparquet (>=2022.11.0,<2023.0.0)
Requires-Dist: pandas (>=1.5.0,<2.0.0)
Requires-Dist: pyspark (>=3.3.0,<3.4.0)
